nuwavsource/__init__.py
nuwavsource/nuwavsource.py
nuwavsource/setup.py
nuwavsource/badpix_headers/nuAuserbadpixDET0.txt
nuwavsource/badpix_headers/nuAuserbadpixDET1.txt
nuwavsource/badpix_headers/nuAuserbadpixDET2.txt
nuwavsource/badpix_headers/nuAuserbadpixDET3.txt
nuwavsource/badpix_headers/nuAuserbadpix_main.txt
nuwavsource/badpix_headers/nuBuserbadpixDET0.txt
nuwavsource/badpix_headers/nuBuserbadpixDET1.txt
nuwavsource/badpix_headers/nuBuserbadpixDET2.txt
nuwavsource/badpix_headers/nuBuserbadpixDET3.txt
nuwavsource/badpix_headers/nuBuserbadpix_main.txt
nuwavsource/nuwavsource/__init__.py
nuwavsource/nuwavsource/nuwavsource.py
nuwavsource/pixpos/nuApixpos20100101v007.fits
nuwavsource/pixpos/nuBpixpos20100101v007.fits
nuwavsource/pixpos/ref_pixA0.npy
nuwavsource/pixpos/ref_pixA1.npy
nuwavsource/pixpos/ref_pixA2.npy
nuwavsource/pixpos/ref_pixA3.npy
nuwavsource/pixpos/ref_pixB0.npy
nuwavsource/pixpos/ref_pixB1.npy
nuwavsource/pixpos/ref_pixB2.npy
nuwavsource/pixpos/ref_pixB3.npy
nuwavsource-0.0.8.dist-info/LICENSE.md
nuwavsource-0.0.8.dist-info/METADATA
nuwavsource-0.0.8.dist-info/WHEEL
nuwavsource-0.0.8.dist-info/top_level.txt
nuwavsource-0.0.8.dist-info/RECORD
