Metadata-Version: 2.1
Name: nuwavsource
Version: 0.0.8
Summary: A package for source exclusion in NuStar observation data using wavelet decomposition
Home-page: https://github.com/Andreyousan/nuwavsource
Author: Andrey Mukhin
Author-email: amukhin@phystech.edu
Classifier: Programming Language :: Python :: 3
Classifier: License :: OSI Approved :: MIT License
Classifier: Operating System :: OS Independent
License-File: LICENSE.md
Requires-Dist: astropy (==5.1)
Requires-Dist: numpy (==1.23.2)
Requires-Dist: pandas (==1.4.4)
Requires-Dist: scipy (==1.9.1)
Requires-Dist: setuptools (==57.4.0)
